LICENSE.txt
MANIFEST.in
README.rst
setup.cfg
setup.py
versioneer.py
vlfeat/__init__.py
vlfeat/_version.py
vlfeat/download.py
vlfeat/dsift.py
vlfeat/imsmooth.py
vlfeat/kmeans.py
vlfeat/phow.py
vlfeat/utils.py
vlfeat/vl_ctypes.py
vlfeat_ctypes.egg-info/PKG-INFO
vlfeat_ctypes.egg-info/SOURCES.txt
vlfeat_ctypes.egg-info/dependency_links.txt
vlfeat_ctypes.egg-info/not-zip-safe
vlfeat_ctypes.egg-info/requires.txt
vlfeat_ctypes.egg-info/top_level.txt