Metadata-Version: 1.1
Name: vlfeat-ctypes
Version: 0.1.5
Summary: A minimal ctypes-based port of some vlfeat functions.
Home-page: https://github.com/dougalsutherland/vlfeat-ctypes
Author: Dougal J. Sutherland
Author-email: dougal@gmail.com
License: BSD
Platform: UNKNOWN
Classifier: Development Status :: 2 - Pre-Alpha
Classifier: Intended Audience :: Science/Research
Classifier: License :: OSI Approved :: BSD License
Classifier: Operating System :: OS Independent
Classifier: Programming Language :: Python :: 2
Classifier: Programming Language :: Python :: 2.7
Classifier: Programming Language :: Python :: 2 :: Only
Classifier: Programming Language :: Python :: Implementation :: CPython
Classifier: Topic :: Scientific/Engineering :: Image Recognition
